ousia/__init__.py
ousia/core.py
ousia-0.2.0.dist-info/METADATA
ousia-0.2.0.dist-info/WHEEL
ousia-0.2.0.dist-info/licenses/LICENSE
ousia-0.2.0.dist-info/RECORD
