Metadata-Version: 2.4
Name: ousia
Version: 0.2.0
Summary: Python implementation of thing architecture.
Project-URL: Homepage, https://github.com/arikanbu/PyThing
Project-URL: Repository, https://github.com/arikanbu/PyThing
Author-email: Bugra Kadir Arikan <kadirbugraa@gmail.com>
License: BSD 3-Clause License
License-File: LICENSE
Keywords: architecture,ousia,preliminary,thing
Classifier: License :: OSI Approved :: BSD License
Requires-Python: >=3.8
